islog/__init__.py
islog/main.py
islog-0.1.0.dist-info/entry_points.txt
islog-0.1.0.dist-info/WHEEL
islog-0.1.0.dist-info/METADATA
islog-0.1.0.dist-info/LICENSE
islog-0.1.0.dist-info/RECORD
