Metadata-Version: 2.1
Name: islog
Version: 0.1.0
Summary: UNKNOWN
License: Apache-2.0
Author-email: Yang Keming <kemingy94@gmail.com>
Requires-Python: >=3.7
Classifier: Development Status :: 4 - Beta
Classifier: Programming Language :: Python :: 3
Classifier: Programming Language :: Python :: 3.10
Classifier: Programming Language :: Python :: 3.7
Classifier: Programming Language :: Python :: 3.8
Classifier: Programming Language :: Python :: 3.9
Classifier: Topic :: Software Development :: Build Tools
Requires-Dist: PyGithub~=1.55
Project-URL: documentation, https://kemingy.github.io/islog
Project-URL: homepage, https://github.com/kemingy/islog
Project-URL: repository, https://github.com/kemingy/islog
